IGram/__init__.py
IGram-0.0.25.dist-info/LICENSE
IGram-0.0.25.dist-info/METADATA
IGram-0.0.25.dist-info/WHEEL
IGram-0.0.25.dist-info/top_level.txt
IGram-0.0.25.dist-info/RECORD
