Metadata-Version: 2.1
Name: IGram
Version: 0.0.25
Summary: InstaGram Scrapper
Author: Vaibhav Pandey
Author-email: pandey.vaibhav3110@gmail.com
Keywords: Instagram info,webscrapping,instagram id name,IGram,insta scrapper,webscrapper,beautifulsoup,vaibhavpandey module,vaibhav pandey python module,Instagram by pyhton
Classifier: Development Status :: 1 - Planning
Classifier: Intended Audience :: Developers
Classifier: Programming Language :: Python :: 3
Classifier: Operating System :: Unix
Classifier: Operating System :: MacOS :: MacOS X
Classifier: Operating System :: Microsoft :: Windows
License-File: LICENSE
Requires-Dist: requests
Requires-Dist: json
Requires-Dist: bs4
